odoo8_addon_shopinvader_price_per_qty-8.0.1.0.0.99.dev3-py3.8-nspkg.pth
odoo_addons/shopinvader_price_per_qty/README.rst
odoo_addons/shopinvader_price_per_qty/__init__.py
odoo_addons/shopinvader_price_per_qty/__openerp__.py
odoo_addons/shopinvader_price_per_qty/demo/pricelist_demo.xml
odoo_addons/shopinvader_price_per_qty/models/__init__.py
odoo_addons/shopinvader_price_per_qty/models/product.py
odoo_addons/shopinvader_price_per_qty/tests/__init__.py
odoo_addons/shopinvader_price_per_qty/tests/test_product.py
odoo8_addon_shopinvader_price_per_qty-8.0.1.0.0.99.dev3.dist-info/METADATA
odoo8_addon_shopinvader_price_per_qty-8.0.1.0.0.99.dev3.dist-info/WHEEL
odoo8_addon_shopinvader_price_per_qty-8.0.1.0.0.99.dev3.dist-info/namespace_packages.txt
odoo8_addon_shopinvader_price_per_qty-8.0.1.0.0.99.dev3.dist-info/top_level.txt
odoo8_addon_shopinvader_price_per_qty-8.0.1.0.0.99.dev3.dist-info/RECORD
