Metadata-Version: 2.1
Name: odoo8-addon-shopinvader-price-per-qty
Version: 8.0.1.0.0.99.dev3
Summary: Shopinvader price per quantity
Home-page: https://akretion.com
Author: Akretion
License: AGPL-3
Platform: UNKNOWN
Classifier: Programming Language :: Python
Classifier: Framework :: Odoo
Classifier: License :: OSI Approved :: GNU Affero General Public License v3
Requires-Python: ~=2.7
Requires-Dist: odoo8-addon-shopinvader
Requires-Dist: odoo (<9.0a,>=8.0a)
